cocotbext/i2c/__init__.py
cocotbext/i2c/i2c_device.py
cocotbext/i2c/i2c_master.py
cocotbext/i2c/i2c_memory.py
cocotbext/i2c/version.py
cocotbext_i2c-0.1.2.dist-info/licenses/LICENSE
cocotbext_i2c-0.1.2.dist-info/METADATA
cocotbext_i2c-0.1.2.dist-info/WHEEL
cocotbext_i2c-0.1.2.dist-info/top_level.txt
cocotbext_i2c-0.1.2.dist-info/RECORD
