Metadata-Version: 2.4
Name: cocotbext-i2c
Version: 0.1.2
Summary: I2C modules for cocotb
Home-page: https://github.com/alexforencich/cocotbext-i2c
Download-URL: https://github.com/alexforencich/cocotbext-i2c/tarball/master
Author: Alex Forencich
Author-email: alex@alexforencich.com
License: MIT
Project-URL: Bug Tracker, https://github.com/alexforencich/cocotbext-i2c/issues
Project-URL: Source Code, https://github.com/alexforencich/cocotbext-i2c
Keywords: i2c,cocotb
Platform: any
Classifier: Development Status :: 3 - Alpha
Classifier: Framework :: cocotb
Classifier: License :: OSI Approved :: MIT License
Classifier: Operating System :: OS Independent
Classifier: Programming Language :: Python :: 3
Classifier: Topic :: Scientific/Engineering :: Electronic Design Automation (EDA)
Requires-Python: >=3.6
License-File: LICENSE
Requires-Dist: cocotb>=1.6.0
Provides-Extra: test
Requires-Dist: pytest; extra == "test"
Requires-Dist: cocotb-test; extra == "test"
Dynamic: download-url
Dynamic: license-file
